{"playlists":{"Samba":["Adoniran Barbosa - Saudosa Maloca.txt","Dorival Caymmi - Samba da Minha Terra.txt","Fundo de Quintal - Nosso Grito.txt","Fundo de Quintal - Vai Lá, Vai Lá!.txt","Os Originais do Samba - Esperanças Perdidas.txt","Os Paralamas do Sucesso - Meu Erro.txt"],"Rock":["Engenheiros do Hawaii - Infinita Highway.txt","RPM - RÃƒÆ’Ã‚Â¡dio Pirata.txt"],"Internacional":["America - A Horse With No Name.txt","America - Ventura HighWay.txt"]},"configuracoes":{"autoStartTime":5,"autoStartVoiceTime":5,"voiceCommandWord":"sargento","showVoiceCommandModal":true,"darkMode":false}}